AHT20_sensor_control/AHT20_sensor_parameters.py
AHT20_sensor_control/AHT20_sensor_wrapper.py
AHT20_sensor_control/I2C_wrapper.py
AHT20_sensor_control/__init__.py
AHT20_sensor_control/__main__.py
AHT20_sensor_control/crc8_helper.py
AHT20_sensor_control/helper_function.py
DHT11_sensor_control/DHT11_wrapper.py
DHT11_sensor_control/__init__.py
DHT11_sensor_control/__main__.py
DHT11_sensor_control/helper_function.py
serial_monitor/__init__.py
serial_monitor/__main__.py
serial_monitor/helper_function.py
sensors_control_gpio_xzf8971-2.2.0.dist-info/LICENSE
sensors_control_gpio_xzf8971-2.2.0.dist-info/METADATA
sensors_control_gpio_xzf8971-2.2.0.dist-info/WHEEL
sensors_control_gpio_xzf8971-2.2.0.dist-info/top_level.txt
sensors_control_gpio_xzf8971-2.2.0.dist-info/RECORD
