Metadata-Version: 2.1
Name: sensors-control-gpio-xzf8971
Version: 2.2.0
Summary: This is a repository desgined for the arduino 37 sensors bundle for raspberry pi 4. This package implemented in raspberry pi 4B GPIO with RPi.GPIO.
Author-email: Zifeng <zifeng.xu@foxmail.com>
Project-URL: Homepage, https://github.com/xzf89718/sensors-control-gpio
Project-URL: Bug Tracker, https://github.com/xzf89718/sensors-control-gpio/issues
Classifier: Programming Language :: Python :: 3
Classifier: License :: OSI Approved :: MIT License
Classifier: Operating System :: OS Independent
Requires-Python: >=3
License-File: LICENSE
